setup.cfg
setup.py
ckanclient/__init__.py
ckanclient/datastore.py
ckanclient.egg-info/PKG-INFO
ckanclient.egg-info/SOURCES.txt
ckanclient.egg-info/dependency_links.txt
ckanclient.egg-info/top_level.txt
ckanclient/loaders/__init__.py
ckanclient/loaders/base.py
ckanclient/tests/__init__.py
ckanclient/tests/test_ckanclient.py
ckanclient/tests/test_datastore.py