Metadata-Version: 1.0
Name: ckanclient
Version: 0.10
Summary: Python client for the CKAN API.
Home-page: https://github.com/okfn/ckanclient
Author: Open Knowledge Foundation
Author-email: info@okfn.org
License: MIT
Keywords: data packaging component tool client
Platform: UNKNOWN
Classifier: Development Status :: 4 - Beta
Classifier: Intended Audience :: Developers
Classifier: Operating System :: OS Independent
Classifier: Programming Language :: Python
Classifier: Topic :: Software Development :: Libraries :: Python Modules
